pangea_api/__init__.py
pangea_api/analysis_result.py
pangea_api/blob_constructors.py
pangea_api/constants.py
pangea_api/file_system_cache.py
pangea_api/knex.py
pangea_api/organization.py
pangea_api/pipeline.py
pangea_api/remote_object.py
pangea_api/sample.py
pangea_api/sample_group.py
pangea_api/user.py
pangea_api/utils.py
pangea_api/work_orders.py
pangea_api/cli/__init__.py
pangea_api/cli/add.py
pangea_api/cli/constants.py
pangea_api/cli/create.py
pangea_api/cli/delete.py
pangea_api/cli/download.py
pangea_api/cli/list.py
pangea_api/cli/main.py
pangea_api/cli/upload.py
pangea_api/cli/user.py
pangea_api/cli/utils.py
pangea_api/contrib/__init__.py
pangea_api/contrib/ncbi/__init__.py
pangea_api/contrib/ncbi/api.py
pangea_api/contrib/ncbi/bioproject.py
pangea_api/contrib/ncbi/cli.py
pangea_api/contrib/ncbi/setup_logging.py
pangea_api/contrib/tagging/__init__.py
pangea_api/contrib/tagging/cli.py
pangea_api/contrib/tagging/tag.py
pangea_api/contrib/tagging/tag_funcs.py
tests/__init__.py
tests/test_api_client.py
tests/test_contrib.py
tests/test_work_orders.py
pangea_api-0.9.23.dist-info/METADATA
pangea_api-0.9.23.dist-info/WHEEL
pangea_api-0.9.23.dist-info/entry_points.txt
pangea_api-0.9.23.dist-info/top_level.txt
pangea_api-0.9.23.dist-info/RECORD
