Metadata-Version: 2.1
Name: pangea-api
Version: 0.9.23
Summary: UNKNOWN
Home-page: UNKNOWN
Author: David C. Danko
Author-email: dcdanko@gmail.com
License: UNKNOWN
Platform: UNKNOWN
Classifier: Intended Audience :: Developers
Classifier: License :: OSI Approved :: MIT License
Classifier: Natural Language :: English
Classifier: Programming Language :: Python :: 3
Requires-Dist: requests
Requires-Dist: click
Requires-Dist: pandas
Requires-Dist: biopython
